pagekey_semver/__init__.py
pagekey_semver/changelog_writer.py
pagekey_semver/cli.py
pagekey_semver/config.py
pagekey_semver/file_replacer/__init__.py
pagekey_semver/file_replacer/base.py
pagekey_semver/file_replacer/json.py
pagekey_semver/file_replacer/sed.py
pagekey_semver/file_replacer/toml.py
pagekey_semver/file_replacer/yaml.py
pagekey_semver/git/__init__.py
pagekey_semver/git/effector.py
pagekey_semver/git/manager.py
pagekey_semver/git/querier.py
pagekey_semver/integrations/__init__.py
pagekey_semver/integrations/release_creator.py
pagekey_semver/models.py
pagekey_semver/release.py
pagekey_semver/util/__init__.py
pagekey_semver/util/command_runner.py
pagekey_semver/util/dynamic_import.py
pagekey_semver/util/env_to_dict.py
pagekey_semver/util/update_dict.py
pagekey_semver-2.0.1.dist-info/LICENSE.md
pagekey_semver-2.0.1.dist-info/METADATA
pagekey_semver-2.0.1.dist-info/WHEEL
pagekey_semver-2.0.1.dist-info/entry_points.txt
pagekey_semver-2.0.1.dist-info/RECORD
