Metadata-Version: 2.1
Name: pagekey-semver
Version: 2.0.1
Summary: Simple, opinionated semantic versioning package.
Author: steve
Requires-Python: >=3.10
Classifier: Programming Language :: Python :: 3
Classifier: Programming Language :: Python :: 3.10
Classifier: Programming Language :: Python :: 3.11
Classifier: Programming Language :: Python :: 3.12
Requires-Dist: pydantic (>=2.9.1,<3.0.0)
Requires-Dist: pyyaml (>=6.0.1,<7.0.0)
Requires-Dist: requests (>=2.32.3,<3.0.0)
Requires-Dist: toml (>=0.10.2,<0.11.0)
